raww/__init__.py
raww/config.py
raww/data/__init__.py
raww/data/active_session.py
raww/data/data.py
raww/data/session.py
raww/data/time.py
raww/sessions.py
raww/tags.py
raww/views.py
raww-1.3.2.dist-info/METADATA
raww-1.3.2.dist-info/WHEEL
raww-1.3.2.dist-info/entry_points.txt
raww-1.3.2.dist-info/RECORD
