Metadata-Version: 2.3
Name: raww
Version: 1.3.2
Summary: A CLI tool for tracking study and work time🦇
Author: dvodnenko
Author-email: thekovalskii@gmail.com
Requires-Python: >=3.10
Classifier: Programming Language :: Python :: 3
Classifier: Programming Language :: Python :: 3.10
Classifier: Programming Language :: Python :: 3.11
Classifier: Programming Language :: Python :: 3.12
Classifier: Programming Language :: Python :: 3.13
Requires-Dist: click (>=8.2.1,<9.0.0)
